{"cameraMode":{"drawMode":0,"name":"Shaded","section":"Shading Mode"},"sceneLighting":true,"audioPlay":false,"sceneViewState":{"showFog":true,"showMaterialUpdate":false,"showSkybox":true,"showFlares":true,"showImageEffects":true,"showParticleSystems":true},"in2DMode":false,"pivot":{"x":0.45604509115219118,"y":1.6394017934799195,"z":3.1210849285125734},"rotation":{"x":0.005665960721671581,"y":-0.9922525882720947,"z":0.049465592950582507,"w":0.11390268057584763},"size":2.857883930206299,"orthographic":false}